case.py
truecase.py
truecaser.py
truecaser-0.0.7.dist-info/LICENSE.txt
truecaser-0.0.7.dist-info/METADATA
truecaser-0.0.7.dist-info/WHEEL
truecaser-0.0.7.dist-info/top_level.txt
truecaser-0.0.7.dist-info/RECORD
