Metadata-Version: 2.1
Name: truecaser
Version: 0.0.7
Summary: Predict and restore word casing
Home-page: UNKNOWN
License: UNKNOWN
Platform: UNKNOWN
Classifier: Programming Language :: Python :: 3
